LICENSE
README.md
setup.py
nintendo/__init__.py
nintendo/miis.py
nintendo/nasc.py
nintendo/nnas.py
nintendo/resources.py
nintendo/files/cert/CTR_Common_Prod_1.der
nintendo/files/cert/CTR_Common_Prod_1.key
nintendo/files/cert/Nintendo_CA_G3.der
nintendo/files/cert/Nintendo_Class_2_CA_G3.der
nintendo/files/cert/Nintendo_Root_CA_G4.der
nintendo/files/cert/Wii_U_Common_Prod_1.der
nintendo/files/cert/Wii_U_Common_Prod_1.key
nintendo/files/config/3ds.cfg
nintendo/files/config/default.cfg
nintendo/files/config/friends.cfg
nintendo/files/config/switch.cfg
nintendo/nex/__init__.py
nintendo/nex/aauser.py
nintendo/nex/account.py
nintendo/nex/authentication.py
nintendo/nex/backend.py
nintendo/nex/common.py
nintendo/nex/datastore.py
nintendo/nex/datastore_miitopia_3ds.py
nintendo/nex/datastore_smm.py
nintendo/nex/datastore_smm2.py
nintendo/nex/debug.py
nintendo/nex/errors.py
nintendo/nex/friends.py
nintendo/nex/health.py
nintendo/nex/hpp.py
nintendo/nex/kerberos.py
nintendo/nex/matchmaking.py
nintendo/nex/matchmaking_eagle.py
nintendo/nex/matchmaking_mhxx.py
nintendo/nex/matchmaking_mk8.py
nintendo/nex/matchmaking_mk8d.py
nintendo/nex/messaging.py
nintendo/nex/monitoring.py
nintendo/nex/natcheck.py
nintendo/nex/nattraversal.py
nintendo/nex/nintendonotification.py
nintendo/nex/notification.py
nintendo/nex/prudp.py
nintendo/nex/ranking.py
nintendo/nex/ranking2.py
nintendo/nex/ranking2_eagle.py
nintendo/nex/ranking_mk8.py
nintendo/nex/ranking_mk8d.py
nintendo/nex/remotelog.py
nintendo/nex/rmc.py
nintendo/nex/screening.py
nintendo/nex/secure.py
nintendo/nex/settings.py
nintendo/nex/streams.py
nintendo/nex/subscriber.py
nintendo/nex/utility.py
nintendo/switch/__init__.py
nintendo/switch/aauth.py
nintendo/switch/atumn.py
nintendo/switch/baas.py
nintendo/switch/common.py
nintendo/switch/dauth.py
nintendo/switch/dragons.py
nintendo/switch/five.py
nintendo/switch/sun.py
nintendoclients.egg-info/PKG-INFO
nintendoclients.egg-info/SOURCES.txt
nintendoclients.egg-info/dependency_links.txt
nintendoclients.egg-info/requires.txt
nintendoclients.egg-info/top_level.txt