Metadata-Version: 2.4
Name: nintendoclients
Version: 4.1.0
Summary: Nintendo network library
Home-page: https://github.com/kinnay/NintendoClients
Author: Yannik Marchand
Author-email: ymarchand@me.com
License: MIT
License-File: LICENSE
Requires-Dist: anynet~=1.1
Requires-Dist: pycryptodome
Dynamic: author
Dynamic: author-email
Dynamic: description
Dynamic: home-page
Dynamic: license
Dynamic: license-file
Dynamic: requires-dist
Dynamic: summary
